{
  "tags": [
    {
      "name": "release",
      "version": "3.2.1.5070",
      "commit": "c99316f",
      "upstream": "master",
      "lastUpdated": "2021-05-28T12:05:42.655Z"
    },
    {
      "name": "testing",
      "version": "3.2.1.5070",
      "commit": "6626a14",
      "upstream": "develop",
      "lastUpdated": "2021-05-28T12:05:55.651Z"
    },
    {
      "name": "nightly",
      "version": "4.0.0.5077",
      "commit": "2589ecc",
      "upstream": "nightly",
      "lastUpdated": "2021-05-31T04:03:52.909Z"
    },
    {
      "name": "musl",
      "version": "4.0.0.5077",
      "commit": "fa32d8b",
      "upstream": "nightly",
      "lastUpdated": "2021-05-31T04:03:10.877Z"
    }
  ],
  "pulls": 41140508,
  "stars": 25
}
